fastapi_bearer_authzn/__init__.py
fastapi_bearer_authzn/__main__.py
fastapi_bearer_authzn/core.py
fastapi_bearer_authzn/py.typed
fastapi_bearer_authzn/cli/__init__.py
fastapi_bearer_authzn-0.3.1.dist-info/METADATA
fastapi_bearer_authzn-0.3.1.dist-info/WHEEL
fastapi_bearer_authzn-0.3.1.dist-info/entry_points.txt
fastapi_bearer_authzn-0.3.1.dist-info/licenses/LICENSE
fastapi_bearer_authzn-0.3.1.dist-info/RECORD
