Metadata-Version: 2.4
Name: fastapi-bearer-authzn
Version: 0.3.1
Summary: A robust bearer token authentication and authorization middleware for FastAPI applications.
Project-URL: Homepage, https://www.syseleven.de/
Project-URL: Repository, https://github.com/syseleven/fastapi-bearer-authzn
Project-URL: Changelog, https://github.com/syseleven/fastapi-bearer-authzn/blob/main/CHANGELOG.md
Author: SysEleven GmbH
License-Expression: MIT
License-File: LICENSE
Keywords: authentication,authn,authorization,authz,bearer,fastapi,middleware,token
Requires-Python: >=3.8
Requires-Dist: typing-extensions>=4.12.2
